gepevolver/__init__.py
gepevolver/engine.py
gepevolver/glyphs.py
gepevolver/karva.py
gepevolver-0.2.0.dist-info/licenses/LICENSE
gepevolver-0.2.0.dist-info/METADATA
gepevolver-0.2.0.dist-info/WHEEL
gepevolver-0.2.0.dist-info/top_level.txt
gepevolver-0.2.0.dist-info/RECORD
