Metadata-Version: 2.4
Name: gepevolver
Version: 0.2.0
Summary: Gene Expression Programming engine for discovering elegant mathematical formulas
Author-email: Nicholas David Brown <worldbridgerstudios@gmail.com>
License: MIT
Project-URL: Homepage, https://github.com/worldbridgerstudios/GEPEvolver
Project-URL: Repository, https://github.com/worldbridgerstudios/GEPEvolver
Keywords: genetic-programming,gene-expression-programming,GEP,formula-discovery,evolutionary-computation,symbolic-regression,mathematical-formulas
Classifier: Development Status :: 4 - Beta
Classifier: Intended Audience :: Science/Research
Classifier: License :: OSI Approved :: MIT License
Classifier: Programming Language :: Python :: 3
Classifier: Programming Language :: Python :: 3.9
Classifier: Programming Language :: Python :: 3.10
Classifier: Programming Language :: Python :: 3.11
Classifier: Programming Language :: Python :: 3.12
Classifier: Topic :: Scientific/Engineering :: Mathematics
Classifier: Topic :: Scientific/Engineering :: Artificial Intelligence
Requires-Python: >=3.9
License-File: LICENSE
Dynamic: license-file
